icalevnt/__init__.py
icalevnt/icaldownload.py
icalevnt/icalevents.py
icalevnt/icalparser.py
icalevnt-0.1.26.dist-info/LICENSE
icalevnt-0.1.26.dist-info/WHEEL
icalevnt-0.1.26.dist-info/METADATA
icalevnt-0.1.26.dist-info/RECORD
