Metadata-Version: 2.1
Name: icalevnt
Version: 0.1.26
Summary: Simple Python 3 library to download, parse and query iCal sources.
License: MIT Licence
Author: Martin Eigenmann
Author-email: github@eigenmannmartin.ch
Requires-Python: >=3.9,<4.0
Classifier: License :: Other/Proprietary License
Classifier: Programming Language :: Python :: 3
Classifier: Programming Language :: Python :: 3.10
Classifier: Programming Language :: Python :: 3.9
Requires-Dist: DateTime (==4.3)
Requires-Dist: httplib2 (==0.20.1)
Requires-Dist: icalendar (==4.0.8)
Requires-Dist: python-dateutil (==2.8.2)
Requires-Dist: pytz (==2021.3)
